cryocat/__init__.py
cryocat/classutils.py
cryocat/cli.py
cryocat/cryomap.py
cryocat/cryomask.py
cryocat/cryomotl.py
cryocat/exceptions.py
cryocat/fsc.py
cryocat/geom.py
cryocat/imod.py
cryocat/ioutils.py
cryocat/mathutils.py
cryocat/mdoc.py
cryocat/memthick.py
cryocat/nnana.py
cryocat/pana.py
cryocat/quadric.py
cryocat/ribana.py
cryocat/scriptutils.py
cryocat/sta.py
cryocat/starfileio.py
cryocat/structure.py
cryocat/surfsamp.py
cryocat/tango.py
cryocat/tgeometry.py
cryocat/tiltstack.py
cryocat/tmana.py
cryocat/visplot.py
cryocat/wedgeutils.py
cryocat-0.7.1.dist-info/licenses/LICENSE
cryocat-0.7.1.dist-info/METADATA
cryocat-0.7.1.dist-info/WHEEL
cryocat-0.7.1.dist-info/entry_points.txt
cryocat-0.7.1.dist-info/top_level.txt
cryocat-0.7.1.dist-info/RECORD
