Metadata-Version: 2.4
Name: cryoCAT
Version: 0.7.1
Summary: Contextual Analysis Tools for CryoET
Author-email: Beata Turonova <beata.turonova@gmail.com>
License: GPLv3+
Project-URL: Homepage, https://github.com/turonova/cryoCAT
Project-URL: Bug Tracker, https://github.com/turonova/cryoCAT/issues
Classifier: Intended Audience :: Science/Research
Classifier: Programming Language :: Python :: 3
Classifier: License :: OSI Approved :: GNU General Public License v3 or later (GPLv3+)
Classifier: Operating System :: OS Independent
Requires-Python: >=3.9
License-File: LICENSE
Requires-Dist: numpy>=1.23
Requires-Dist: pandas>=1.5
Requires-Dist: matplotlib>=3.6
Requires-Dist: scipy>=1.9.1
Requires-Dist: scikit-image>=0.20.0
Requires-Dist: emfile>=0.3.0
Requires-Dist: mrcfile>=1.4.3
Requires-Dist: seaborn>=0.12.1
Requires-Dist: scikit-learn>=1.0.2
Requires-Dist: lmfit>=1.2.2
Requires-Dist: h5py>=3.10.0
Requires-Dist: numba>=0.60.0
Requires-Dist: pyyaml>=6.0.1
Requires-Dist: tqdm>=4.66.1
Requires-Dist: plotly>=5.24
Requires-Dist: dash>=3.0.1
Requires-Dist: dash_bootstrap_components>=2.0
Requires-Dist: dash_ag_grid>=31.3.1
Requires-Dist: networkx>=3.1
Requires-Dist: numpydoc>=1.9
Dynamic: license-file
